volvopy/__init__.py
volvopy/volvo_api.py
volvopy/settings/__init__.py
volvopy/settings/connected-vehicle-c3-specification.v1.json
volvopy/settings/connected-vehicle-c3-specification.v2.json
volvopy/settings/constants.py
volvopy/settings/energy-api-specification.v1.json
volvopy/settings/extended-vehicle-c3-specification.v1.json
volvopy/settings/location-specification.v1.json
volvopy-0.1.21.dist-info/METADATA
volvopy-0.1.21.dist-info/WHEEL
volvopy-0.1.21.dist-info/licenses/LICENSE
volvopy-0.1.21.dist-info/RECORD
