Metadata-Version: 2.1
Name: volvopy
Version: 0.1.21
Summary: Connect to the Volvo API using Python.
Project-URL: Homepage, https://github.com/Mausy5043/volvopy
Project-URL: Bug Tracker, https://github.com/Mausy5043/volvopy/issues
Author: Mausy5043
License-Expression: MIT
License-File: LICENSE
Classifier: Development Status :: 4 - Beta
Classifier: License :: OSI Approved :: MIT License
Classifier: Operating System :: OS Independent
Classifier: Programming Language :: Python :: 3.8
Classifier: Programming Language :: Python :: 3.9
Classifier: Programming Language :: Python :: 3.10
Classifier: Programming Language :: Python :: 3.11
Classifier: Topic :: Home Automation
Requires-Python: >=3.8
